{
  "all_docs": [
    {
      "_id": "1",
      "_rev": "1-031415f1c97b282980861369e3cf56af",
      "conversation_id": "fd7bb5b2-a49e-4f17-8a9f-381281499390",
      "user_confirma_agendamento": "sim",
      "user_date": "2024-02-02",
      "user_name": "Toin",
      "user_selecao_categoria": "Categoria: Barba",
      "user_selecao_servico2": "designer barba",
      "user_time": "01:00:00"
    },
    {
      "_id": "7",
      "_rev": "1-84522f8be62c05418dbdf8ef4ce66e4e",
      "channel": "chat",
      "conversation_id": "6cf82327-3fc9-4051-a218-06ebcccaa2ad",
      "origem": "https://web-chat.global.assistant.watson.appdomain.cloud/preview.html",
      "request_timestamp": "2023-04-17T20:50:46.625Z",
      "user_confirma_agendamento": "sim",
      "user_date": "2023-04-22",
      "user_name": "Danielson",
      "user_selecao_categoria": "Categoria: Cabelo",
      "user_selecao_servico2": "penteado",
      "user_time": "10:00:00"
    },
    {
      "_id": "8",
      "_rev": "1-30f7416309a583081f11bbf1e346c624",
      "channel": "chat",
      "conversation_id": "df28fbb0-fae6-40b1-b353-037b873b64ee",
      "origem": "https://web-chat.global.assistant.watson.appdomain.cloud/preview.html",
      "request_timestamp": "2023-04-17T22:10:27.810Z",
      "user_confirma_agendamento": "sim",
      "user_date": "2023-04-18",
      "user_name": "Daniel",
      "user_selecao_categoria": "Categoria: Barba",
      "user_selecao_servico2": "barboterapia",
      "user_time": "09:00:00"
    },
    {
      "_id": "9",
      "_rev": "3-889b7387d455b1be81cacdf5b17c0e4b",
      "channel": "facebook",
      "conversation_id": "242705d3-d49b-4b96-8c4d-b39ccbe543cc",
      "origem": "Facebook Messenger",
      "request_timestamp": "2023-04-18T03:14:24.293Z",
      "user_confirma_agendamento": "sim",
      "user_date": "2023-07-08",
      "user_name": "TesteFace",
      "user_selecao_categoria": "Categoria: Barba",
      "user_selecao_servico2": "pigmentacao",
      "user_time": "04:15:00"
    },
    {
      "_id": "10",
      "_rev": "1-5140e0235b4e792fd539b534dbfff4bb",
      "channel": "chat",
      "conversation_id": "5813a6e0-ad75-44b7-99a1-12fab0c9b311",
      "origem": "https://web-chat.global.assistant.watson.appdomain.cloud/preview.html",
      "request_timestamp": "2023-04-18T15:22:34.958Z",
      "user_confirma_agendamento": "sim",
      "user_date": "2023-06-01",
      "user_name": "TesteAction",
      "user_selecao_categoria": "Categoria: Barba",
      "user_selecao_servico2": "designer barba",
      "user_time": "12:23:00"
    },
    {
      "_id": "11",
      "_rev": "13-11079912939738489281c2127e2dd310",
      "conversation_id": "487ae7e9-2361-4424-9234-0c1f47cb707b",
      "user_confirma_agendamento": "sim",
      "user_date": "2023-07-06",
      "user_name": "789",
      "user_selecao_categoria": "Categoria: Barba",
      "user_selecao_servico2": "designer barba",
      "user_time": "04:45:00"
    },
    {
      "_id": "12",
      "_rev": "5-9e009318c0b39c5ddcc70f2ad4ab4d67",
      "conversation_id": "660e849c-1119-4205-90c5-12b4a151ad14",
      "user_confirma_agendamento": "sim",
      "user_date": "2023-05-12",
      "user_name": "K",
      "user_selecao_categoria": "Categoria: Barba",
      "user_selecao_servico2": "designer barba",
      "user_time": "06:45:00"
    },
    {
      "_id": "13",
      "_rev": "5-ae80ceb8fc508ab6ed02ede5482427c2",
      "channel": "chat",
      "conversation_id": "bb2c5f31-eb72-47f8-a1dd-f1a911a61ea1",
      "origem": "https://us-east.assistant.watson.cloud.ibm.com/crn%3Av1%3Abluemix%3Apublic%3Aconversation%3Aus-east%3Aa%2Fe7f32c8023244dc1b35ea9b049eaeb76%3A8c4aabba-535d-4821-9105-493d73a4dfa2%3A%3A/assistants/1a82e0b6-bd91-46ef-8ccf-ab44edcfa29c",
      "request_timestamp": "2023-04-19T04:48:50.225Z",
      "user_confirma_agendamento": "sim",
      "user_date": "2023-08-12",
      "user_name": "Fds",
      "user_selecao_categoria": "Categoria: Barba",
      "user_selecao_servico2": "designer barba",
      "user_time": "05:47:00"
    },
    {
      "_id": "2",
      "_rev": "1-52a30cf0c9fca05fc2e2cb9a46787655",
      "channel": "chat",
      "conversation_id": "88eeaf18-92c0-4cb1-bb07-f21e976eea2e",
      "origem": "https://us-east.assistant.watson.cloud.ibm.com/crn%3Av1%3Abluemix%3Apublic%3Aconversation%3Aus-east%3Aa%2Fe7f32c8023244dc1b35ea9b049eaeb76%3A8c4aabba-535d-4821-9105-493d73a4dfa2%3A%3A/assistants/1a82e0b6-bd91-46ef-8ccf-ab44edcfa29c",
      "request_timestamp": "2023-04-15T23:16:47.183Z",
      "user_confirma_agendamento": "sim",
      "user_date": "2023-05-01",
      "user_name": "Toin",
      "user_selecao_categoria": "Categoria: Barba",
      "user_selecao_servico2": "pigmentacao",
      "user_time": "15:00:00"
    },
    {
      "_id": "4",
      "_rev": "1-3ee31b6816a88d8c2994af890c3edb3e",
      "channel": "chat",
      "conversation_id": "0b5bbc7c-bc72-42c0-917d-94c12c50a967",
      "origem": "https://web-chat.global.assistant.watson.appdomain.cloud/preview.html",
      "request_timestamp": "2023-04-15T23:54:06.324Z",
      "user_confirma_agendamento": "sim",
      "user_date": "2023-06-05",
      "user_name": "5",
      "user_selecao_categoria": "Categoria: Barba",
      "user_selecao_servico2": "designer barba",
      "user_time": "03:44:00"
    },
    {
      "_id": "5",
      "_rev": "3-4060065b99e4c9dff0e67b7c01e9d6c0",
      "channel": "chat",
      "conversation_id": "cc9257bd-0414-496a-a627-ca3fff648c39",
      "origem": "https://web-chat.global.assistant.watson.appdomain.cloud/preview.html",
      "request_timestamp": "2023-04-17T02:21:36.329Z",
      "user_confirma_agendamento": "sim",
      "user_date": "2023-05-06",
      "user_name": "Joao",
      "user_selecao_categoria": "Categoria: Cabelo",
      "user_selecao_servico2": "penteado",
      "user_time": "12:11:00"
    },
    {
      "_id": "6",
      "_rev": "3-c7570048606c61f49af8fd433c1a0201",
      "channel": "chat",
      "conversation_id": "1f121d7d-e03f-408e-a81e-8fdb12753241",
      "origem": "https://us-east.assistant.watson.cloud.ibm.com/crn%3Av1%3Abluemix%3Apublic%3Aconversation%3Aus-east%3Aa%2Fe7f32c8023244dc1b35ea9b049eaeb76%3A8c4aabba-535d-4821-9105-493d73a4dfa2%3A%3A/assistants/1a82e0b6-bd91-46ef-8ccf-ab44edcfa29c",
      "request_timestamp": "2023-04-17T15:04:13.846Z",
      "user_confirma_agendamento": "sim",
      "user_date": "2023-09-12",
      "user_name": "Teste2",
      "user_selecao_categoria": "Categoria: Cabelo",
      "user_selecao_servico2": "corte",
      "user_time": "15:00:00"
    }
  ]
}
